pydantic_ai_chat_ui/__init__.py
pydantic_ai_chat_ui/messages/__init__.py
pydantic_ai_chat_ui/messages/full.py
pydantic_ai_chat_ui/messages/shared.py
pydantic_ai_chat_ui/messages/streamed.py
pydantic_ai_chat_ui/py.typed
pydantic_ai_chat_ui/requests.py
pydantic_ai_chat_ui/streaming.py
pydantic_ai_chat_ui/tools.py
pydantic_ai_chat_ui-0.1.0.dist-info/WHEEL
pydantic_ai_chat_ui-0.1.0.dist-info/METADATA
pydantic_ai_chat_ui-0.1.0.dist-info/RECORD
