Metadata-Version: 2.3
Name: pydantic-ai-chat-ui
Version: 0.1.0
Summary: Add your description here
Author: Sam Pratt
Author-email: Sam Pratt <samj.pratt@gmail.com>
Requires-Dist: pydantic-ai-slim>=1.0
Requires-Python: >=3.13
